LICENSE
README.md
setup.py
thsdk/__init__.py
thsdk/_constants.py
thsdk/thsdk.py
thsdk.egg-info/PKG-INFO
thsdk.egg-info/SOURCES.txt
thsdk.egg-info/dependency_links.txt
thsdk.egg-info/requires.txt
thsdk.egg-info/top_level.txt
thsdk/examples/__init__.py
thsdk/examples/big_order_flow.py
thsdk/examples/block.py
thsdk/examples/block_constituents.py
thsdk/examples/call_auction.py
thsdk/examples/call_auction_anomaly.py
thsdk/examples/codes_by_block.py
thsdk/examples/codes_by_market.py
thsdk/examples/concept.py
thsdk/examples/corporate_action.py
thsdk/examples/depth.py
thsdk/examples/depth_details.py
thsdk/examples/forex.py
thsdk/examples/help.py
thsdk/examples/hs300.py
thsdk/examples/industry.py
thsdk/examples/intraday_data.py
thsdk/examples/ipo.py
thsdk/examples/kline.py
thsdk/examples/loop.py
thsdk/examples/market_data_block.py
thsdk/examples/market_data_bond.py
thsdk/examples/market_data_cn.py
thsdk/examples/market_data_forex.py
thsdk/examples/market_data_fund.py
thsdk/examples/market_data_future.py
thsdk/examples/market_data_hk.py
thsdk/examples/market_data_index.py
thsdk/examples/market_data_uk.py
thsdk/examples/market_data_us.py
thsdk/examples/min_snapshot.py
thsdk/examples/normalize_symbol.py
thsdk/examples/query_data.py
thsdk/examples/test_thsdk.py
thsdk/examples/tick_level1.py
thsdk/examples/tick_super_level1.py
thsdk/examples/wencai_nlp.py
thsdk/libs/darwin/__init__.py
thsdk/libs/darwin/hq.dylib
thsdk/libs/linux/__init__.py
thsdk/libs/linux/hq.so
thsdk/libs/windows/__init__.py
thsdk/libs/windows/hq.dll